package net.digitalingot.feather;

public class ja
{
    public static final jo<jj> EE;
    public static final jo<ji> EF;
    public static final jo<jl> EG;
    public static final jo<jk> EH;
    public static final jo<jh> EI;
    public static final jo<jg> EJ;
    
    static {
        // 
        // This method could not be decompiled.
        // 
        // Original Bytecode:
        // 
        //     3: dup            
        //     4: getstatic       net/digitalingot/feather/jj.ER:Lnet/minecraft/client/renderer/vertex/VertexFormat;
        //     7: aconst_null    
        //     8: invokedynamic   BootstrapMethod #0, apply:()Lnet/digitalingot/feather/jo$a;
        //    13: invokespecial   net/digitalingot/feather/jo.<init>:(Lnet/minecraft/client/renderer/vertex/VertexFormat;Ljava/util/function/Function;Lnet/digitalingot/feather/jo$a;)V
        //    16: putstatic       net/digitalingot/feather/ja.EE:Lnet/digitalingot/feather/jo;
        //    19: new             Lnet/digitalingot/feather/jo;
        //    22: dup            
        //    23: getstatic       net/digitalingot/feather/ji.ER:Lnet/minecraft/client/renderer/vertex/VertexFormat;
        //    26: aconst_null    
        //    27: invokedynamic   BootstrapMethod #1, apply:()Lnet/digitalingot/feather/jo$a;
        //    32: invokespecial   net/digitalingot/feather/jo.<init>:(Lnet/minecraft/client/renderer/vertex/VertexFormat;Ljava/util/function/Function;Lnet/digitalingot/feather/jo$a;)V
        //    35: putstatic       net/digitalingot/feather/ja.EF:Lnet/digitalingot/feather/jo;
        //    38: new             Lnet/digitalingot/feather/jo;
        //    41: dup            
        //    42: getstatic       net/digitalingot/feather/jl.ER:Lnet/minecraft/client/renderer/vertex/VertexFormat;
        //    45: aconst_null    
        //    46: invokedynamic   BootstrapMethod #2, apply:()Lnet/digitalingot/feather/jo$a;
        //    51: invokespecial   net/digitalingot/feather/jo.<init>:(Lnet/minecraft/client/renderer/vertex/VertexFormat;Ljava/util/function/Function;Lnet/digitalingot/feather/jo$a;)V
        //    54: putstatic       net/digitalingot/feather/ja.EG:Lnet/digitalingot/feather/jo;
        //    57: new             Lnet/digitalingot/feather/jo;
        //    60: dup            
        //    61: getstatic       net/digitalingot/feather/jk.ER:Lnet/minecraft/client/renderer/vertex/VertexFormat;
        //    64: aconst_null    
        //    65: invokedynamic   BootstrapMethod #3, apply:()Lnet/digitalingot/feather/jo$a;
        //    70: invokespecial   net/digitalingot/feather/jo.<init>:(Lnet/minecraft/client/renderer/vertex/VertexFormat;Ljava/util/function/Function;Lnet/digitalingot/feather/jo$a;)V
        //    73: putstatic       net/digitalingot/feather/ja.EH:Lnet/digitalingot/feather/jo;
        //    76: new             Lnet/digitalingot/feather/jo;
        //    79: dup            
        //    80: getstatic       net/digitalingot/feather/jh.ER:Lnet/minecraft/client/renderer/vertex/VertexFormat;
        //    83: aconst_null    
        //    84: invokedynamic   BootstrapMethod #4, apply:()Lnet/digitalingot/feather/jo$a;
        //    89: invokespecial   net/digitalingot/feather/jo.<init>:(Lnet/minecraft/client/renderer/vertex/VertexFormat;Ljava/util/function/Function;Lnet/digitalingot/feather/jo$a;)V
        //    92: putstatic       net/digitalingot/feather/ja.EI:Lnet/digitalingot/feather/jo;
        //    95: new             Lnet/digitalingot/feather/jo;
        //    98: dup            
        //    99: getstatic       net/digitalingot/feather/jg.ER:Lnet/minecraft/client/renderer/vertex/VertexFormat;
        //   102: aconst_null    
        //   103: invokedynamic   BootstrapMethod #5, apply:()Lnet/digitalingot/feather/jo$a;
        //   108: invokespecial   net/digitalingot/feather/jo.<init>:(Lnet/minecraft/client/renderer/vertex/VertexFormat;Ljava/util/function/Function;Lnet/digitalingot/feather/jo$a;)V
        //   111: putstatic       net/digitalingot/feather/ja.EJ:Lnet/digitalingot/feather/jo;
        //   114: return         
        // 
        // The error that occurred was:
        // 
        // java.lang.NullPointerException
        //     at com.strobel.decompiler.languages.java.ast.NameVariables.generateNameForVariable(NameVariables.java:264)
        //     at com.strobel.decompiler.languages.java.ast.NameVariables.assignNamesToVariables(NameVariables.java:188)
        //     at com.strobel.decompiler.languages.java.ast.AstMethodBodyBuilder.createMethodBody(AstMethodBodyBuilder.java:276)
        //     at com.strobel.decompiler.languages.java.ast.AstMethodBodyBuilder.createMethodBody(AstMethodBodyBuilder.java:99)
        //     at com.strobel.decompiler.languages.java.ast.AstBuilder.createMethodBody(AstBuilder.java:782)
        //     at com.strobel.decompiler.languages.java.ast.AstBuilder.createMethod(AstBuilder.java:675)
        //     at com.strobel.decompiler.languages.java.ast.AstBuilder.addTypeMembers(AstBuilder.java:552)
        //     at com.strobel.decompiler.languages.java.ast.AstBuilder.createTypeCore(AstBuilder.java:519)
        //     at com.strobel.decompiler.languages.java.ast.AstBuilder.createTypeNoCache(AstBuilder.java:161)
        //     at com.strobel.decompiler.languages.java.ast.AstBuilder.createType(AstBuilder.java:150)
        //     at com.strobel.decompiler.languages.java.ast.AstBuilder.addType(AstBuilder.java:125)
        //     at com.strobel.decompiler.languages.java.JavaLanguage.buildAst(JavaLanguage.java:71)
        //     at com.strobel.decompiler.languages.java.JavaLanguage.decompileType(JavaLanguage.java:59)
        //     at us.deathmarine.luyten.FileSaver.doSaveJarDecompiled(FileSaver.java:192)
        //     at us.deathmarine.luyten.FileSaver.access$300(FileSaver.java:45)
        //     at us.deathmarine.luyten.FileSaver$4.run(FileSaver.java:112)
        //     at java.lang.Thread.run(Thread.java:750)
        // 
        throw new IllegalStateException("An error occurred while decompiling this method.");
    }
}
